django_paranoid/__init__.py
django_paranoid/admin.py
django_paranoid/models.py
django_paranoid-1.0.dist-info/LICENSE
django_paranoid-1.0.dist-info/METADATA
django_paranoid-1.0.dist-info/WHEEL
django_paranoid-1.0.dist-info/top_level.txt
django_paranoid-1.0.dist-info/RECORD
