Metadata-Version: 2.1
Name: django-paranoid
Version: 1.0
Summary: this library adds 'created_at', 'updated_at' and 'delete_at'  fields like a rail apps in django, also added soft delete method
Home-page: https://github.com/drneox/django-paranoid
Author: Carlos Ganoza Plasencia
Author-email: cganozap@gmail.com
License: MIT
Keywords: django created_at updated_at deleted_at fields models django-admin soft delete softdelete
Platform: UNKNOWN
